[
    {
        "date": "",
        "time": "",
        "capacity": "",
        "instructor": ""
    },
    {
        "date": "",
        "time": "",
        "capacity": "",
        "instructor": ""
    },
    {
        "date": "donderdag 03 juli",
        "time": "19:00 - 19:45",
        "capacity": "4 / 4",
        "instructor": "Gilltumn Vanhauwaert"
    },
    {
        "date": "",
        "time": "",
        "capacity": "",
        "instructor": ""
    },
    {
        "date": "",
        "time": "",
        "capacity": "",
        "instructor": ""
    },
    {
        "date": "",
        "time": "",
        "capacity": "",
        "instructor": ""
    },
    {
        "date": "",
        "time": "",
        "capacity": "",
        "instructor": ""
    },
    {
        "date": "",
        "time": "",
        "capacity": "",
        "instructor": ""
    }
]